pglogginghandler/__init__.py
pglogginghandler/log_handler.py
pglogginghandler-0.3.dist-info/METADATA
pglogginghandler-0.3.dist-info/WHEEL
pglogginghandler-0.3.dist-info/licenses/LICENSE
pglogginghandler-0.3.dist-info/RECORD
